LICENSE
README.md
setup.py
orbital_surface.egg-info/PKG-INFO
orbital_surface.egg-info/SOURCES.txt
orbital_surface.egg-info/dependency_links.txt
orbital_surface.egg-info/entry_points.txt
orbital_surface.egg-info/not-zip-safe
orbital_surface.egg-info/requires.txt
orbital_surface.egg-info/top_level.txt
src/orbital/__init__.py
src/orbital/__main__.py
src/orbital/class_orb_ring.py
src/orbital/class_orb_tools.py
src/orbital/orb_tools.sobj
src/orbital/poly_maps.py
src/orbital/sage_interface.py
src/orbital/surface_in_quadric.py
src/orbital/cossin/__init__.py
src/orbital/cossin/cos_sin.py
src/orbital/cossin/cos_sin.txt
src/orbital/pov/__init__.py
src/orbital/pov/pov_CH1_cyclide.py
src/orbital/pov/pov_blum_cyclide.py
src/orbital/pov/pov_dp6_sing.py
src/orbital/pov/pov_dp6_smooth.py
src/orbital/pov/pov_dp8_clifford.py
src/orbital/pov/pov_horn_cyclide.py
src/orbital/pov/pov_perseus_cyclide.py
src/orbital/pov/pov_quadric_smooth.py
src/orbital/pov/pov_ring_cyclide.py
src/orbital/pov/pov_spindle_cyclide.py
src/orbital/pov/pov_veronese.py
src/orbital/povray/__init__.py
src/orbital/povray/class_pov_input.py
src/orbital/povray/povray.py
src/orbital/povray/povray_aux.py
src/orbital/prod/__init__.py
src/orbital/prod/class_orb_input.py
src/orbital/prod/class_orb_output.py
src/orbital/prod/orb_matrices.py
src/orbital/prod/orb_product.py
src/orbital/sphere/__init__.py
src/orbital/sphere/class_sphere_input.py
src/orbital/sphere/sphere_experiment.py
src/orbital/sphere/sphere_transform.py